{
	"GET_200": {
	  "data": {
	    "success": true,
	    "message": "user profile fetched with succes",
	    "user": {
	      "id": 1,
	      "userStatus": 1,
	      "userType": 3,
	      "name": "Carlos Timóteo",
	      "email": "carlos.timoteo@olx.com",
	      "phone": "967590550",
	      "phone_region": "PT",
	      "username": "ctimoteo",
	      "country": "PT",
	      "company": "Fixeads"
	    }
	  }
	},
	"GET_400": {
	  	"data": {
	    	"success": false,
	    	"message": "Failed to get user profile"
	  	},
	  	"error": {
		    "id": "Exception",
	    	"title": "Token does not exists, cannot return user token data"
	  	}
	}
}
